palm_liner/__init__.py
palm_liner/__main__.py
palm_liner/checkpoint/checkpoint_aug_epoch70.pth
palm_liner/client/__init__.py
palm_liner/client/exceptions.py
palm_liner/client/palm_liner_client.py
palm_liner/common/__init__.py
palm_liner/common/classification.py
palm_liner/common/detection.py
palm_liner/common/measurement.py
palm_liner/common/model.py
palm_liner/common/rectification.py
palm_liner/common/tools.py
palm_liner-0.1.1.dist-info/METADATA
palm_liner-0.1.1.dist-info/WHEEL
palm_liner-0.1.1.dist-info/top_level.txt
palm_liner-0.1.1.dist-info/RECORD
